datetime_truncate/__init__.py
datetime_truncate/datetime_truncate.py
datetime_truncate-1.1.0.dist-info/DESCRIPTION.rst
datetime_truncate-1.1.0.dist-info/METADATA
datetime_truncate-1.1.0.dist-info/RECORD
datetime_truncate-1.1.0.dist-info/WHEEL
datetime_truncate-1.1.0.dist-info/metadata.json
datetime_truncate-1.1.0.dist-info/top_level.txt
