Metadata-Version: 2.0
Name: datetime-truncate
Version: 1.1.0
Summary: Truncate datetime objects to a set level of precision
Home-page: https://github.com/gaqzi/datetime_truncate
Author: Björn Andersson
Author-email: ba@sanitarium.se
License: BSD
Platform: UNKNOWN
Classifier: Intended Audience :: Developers
Classifier: License :: OSI Approved :: BSD License
Classifier: Programming Language :: Python
Classifier: Programming Language :: Python :: 2
Classifier: Programming Language :: Python :: 2.6
Classifier: Programming Language :: Python :: 2.7
Classifier: Programming Language :: Python :: 3
Classifier: Programming Language :: Python :: 3.4
Classifier: Programming Language :: Python :: 3.5
Classifier: Programming Language :: Python :: 3.6
Requires-Dist: six
Requires-Dist: typing
